yarsaw/__init__.py
yarsaw/client.py
yarsaw/data_classes.py
yarsaw/exceptions.py
yarsaw/httpclient.py
yarsaw/utils.py
yarsaw-2.1.0.dist-info/LICENSE
yarsaw-2.1.0.dist-info/METADATA
yarsaw-2.1.0.dist-info/WHEEL
yarsaw-2.1.0.dist-info/top_level.txt
yarsaw-2.1.0.dist-info/RECORD
