Metadata-Version: 2.1
Name: yarsaw
Version: 2.1.0
Summary: An async wrapper for the Random Stuff API
Author: Bruce
Author-email: brucealt69@gmail.com
License: MIT
Project-URL: Documentation, https://yarsaw.namantech.me/
Project-URL: Source, https://github.com/BruceCodesGithub/yarsaw
Project-URL: Tracker, https://github.com/BruceCodesGithub/yarsaw/issues
Keywords: random-stuff-api rsa yarsaw prsaw randomstuff ai-chatbot memes canvas jokes facts all-in-one discord reddit
Platform: UNKNOWN
Classifier: Development Status :: 5 - Production/Stable
Classifier: Topic :: Utilities
Classifier: License :: OSI Approved :: MIT License
License-File: LICENSE
Requires-Dist: aiohttp
